CrewWatch/__init__.py
CrewWatch/cost.py
CrewWatch/logger.py
CrewWatch/monitor.py
CrewWatch/utils.py
CrewWatch/visualizer.py
tests/__init__.py
tests/test.py
CrewWatch-0.0.1.dist-info/METADATA
CrewWatch-0.0.1.dist-info/WHEEL
CrewWatch-0.0.1.dist-info/top_level.txt
CrewWatch-0.0.1.dist-info/RECORD
